letstayinn_package/__init__.py
letstayinn_package/booking_repository.py
letstayinn_package/introduction.py
letstayinn_package/service_request_repository.py
letstayinn_package/models/__init__.py
letstayinn_package/models/bookings.py
letstayinn_package-0.1.1.dist-info/METADATA
letstayinn_package-0.1.1.dist-info/WHEEL
letstayinn_package-0.1.1.dist-info/top_level.txt
letstayinn_package-0.1.1.dist-info/RECORD
