Metadata-Version: 2.4
Name: letstayinn-package
Version: 0.1.1
Summary: DynamoDB repositories and domain utilities for LetStayInn
Author: Shyam Pratap
Requires-Python: >=3.9
Requires-Dist: boto3>=1.34
Requires-Dist: botocore>=1.34
Requires-Dist: mypy-boto3-dynamodb>=1.34
Requires-Dist: pydantic>=2.5
Provides-Extra: dev
Requires-Dist: pytest; extra == "dev"
Requires-Dist: black; extra == "dev"
Requires-Dist: ruff; extra == "dev"
Requires-Dist: mypy; extra == "dev"
